llama_index/tools/google/__init__.py
llama_index/tools/google/calendar/__init__.py
llama_index/tools/google/calendar/base.py
llama_index/tools/google/gmail/__init__.py
llama_index/tools/google/gmail/base.py
llama_index/tools/google/search/__init__.py
llama_index/tools/google/search/base.py
flying_delta_tools_google-0.1.0.dist-info/METADATA
flying_delta_tools_google-0.1.0.dist-info/WHEEL
flying_delta_tools_google-0.1.0.dist-info/RECORD
